force_fusion/__init__.py
force_fusion/app.py
force_fusion/config.py
force_fusion/controller.py
force_fusion/sensors.py
force_fusion/ui_main_window.py
force_fusion/cli/__init__.py
force_fusion/cli/cli.py
force_fusion/cli/env.py
force_fusion/cli/test.py
force_fusion/cli/websocket.py
force_fusion/resources/car_back.svg
force_fusion/resources/car_side.svg
force_fusion/resources/demo.mp4
force_fusion/resources/favicon.png
force_fusion/resources/styles.qss
force_fusion/utils/env_utils.py
force_fusion/utils/geo_utils.py
force_fusion/utils/test_utils.py
force_fusion/utils/websocket_client_test.py
force_fusion/utils/websocket_server.py
force_fusion/widgets/__init__.py
force_fusion/widgets/attitude.py
force_fusion/widgets/gg_diagram.py
force_fusion/widgets/heading.py
force_fusion/widgets/mapbox_view.py
force_fusion/widgets/minimap.py
force_fusion/widgets/speedometer.py
force_fusion/widgets/tire_force.py
force_fusion-0.0.8.dist-info/METADATA
force_fusion-0.0.8.dist-info/WHEEL
force_fusion-0.0.8.dist-info/entry_points.txt
force_fusion-0.0.8.dist-info/licenses/LICENSE
force_fusion-0.0.8.dist-info/RECORD
