Metadata-Version: 2.4
Name: force-fusion
Version: 0.0.8
Summary:  A real-time PyQt dashboard visualizing vehicle dynamics and normal-force distribution.
Project-URL: Homepage, https://github.com/Sang-Buster/Force-Fusion
Project-URL: Documentation, https://deepwiki.com/Sang-Buster/Force-Fusion
Project-URL: Repository, https://github.com/Sang-Buster/Force-Fusion
Author-email: Sang Buster <hello@singsongaftermath.com>
License: MIT License
License-File: LICENSE
Requires-Python: >=3.10
Requires-Dist: folium>=0.19.5
Requires-Dist: pyqt5>=5.15.11
Requires-Dist: pyqtwebengine>=5.15.7
Requires-Dist: websockets>=15.0.0
